chuk_virtual_fs/__init__.py
chuk_virtual_fs/batch_operations.py
chuk_virtual_fs/config.py
chuk_virtual_fs/directory.py
chuk_virtual_fs/exceptions.py
chuk_virtual_fs/file.py
chuk_virtual_fs/file_operations.py
chuk_virtual_fs/fs_manager.py
chuk_virtual_fs/mount_manager.py
chuk_virtual_fs/node_base.py
chuk_virtual_fs/node_info.py
chuk_virtual_fs/path_resolver.py
chuk_virtual_fs/path_utils.py
chuk_virtual_fs/provider_base.py
chuk_virtual_fs/provider_factory.py
chuk_virtual_fs/provider_manager.py
chuk_virtual_fs/retry_handler.py
chuk_virtual_fs/search_utils.py
chuk_virtual_fs/security_config.py
chuk_virtual_fs/security_wrapper.py
chuk_virtual_fs/snapshot_manager.py
chuk_virtual_fs/template_loader.py
chuk_virtual_fs/cli/s3_bucket_cli.py
chuk_virtual_fs/cli/snapshot_cli.py
chuk_virtual_fs/cli/template_cli.py
chuk_virtual_fs/providers/__init__.py
chuk_virtual_fs/providers/e2b.py
chuk_virtual_fs/providers/filesystem.py
chuk_virtual_fs/providers/memory.py
chuk_virtual_fs/providers/pyodide.py
chuk_virtual_fs/providers/s3.py
chuk_virtual_fs/providers/sqlite.py
chuk_virtual_fs-0.2.1.dist-info/licenses/LICENSE.md
chuk_virtual_fs-0.2.1.dist-info/METADATA
chuk_virtual_fs-0.2.1.dist-info/WHEEL
chuk_virtual_fs-0.2.1.dist-info/entry_points.txt
chuk_virtual_fs-0.2.1.dist-info/top_level.txt
chuk_virtual_fs-0.2.1.dist-info/RECORD
