Metadata-Version: 2.4
Name: chuk-virtual-fs
Version: 0.2.1
Summary: A secure, modular virtual filesystem designed for AI agent sandboxes
Author-email: Chris Hay <your.email@example.com>
License: MIT
Project-URL: Homepage, https://github.com/chrishayuk/chuk-virtual-fs
Project-URL: Bug Tracker, https://github.com/chrishayuk/chuk-virtual-fs/issues
Project-URL: Documentation, https://github.com/chrishayuk/chuk-virtual-fs#readme
Keywords: filesystem,virtual,sandbox,ai,security
Classifier: Development Status :: 4 - Beta
Classifier: Intended Audience :: Developers
Classifier: License :: OSI Approved :: MIT License
Classifier: Programming Language :: Python :: 3
Classifier: Programming Language :: Python :: 3.11
Classifier: Programming Language :: Python :: 3.12
Classifier: Topic :: Software Development :: Libraries
Classifier: Topic :: System :: Filesystems
Classifier: Topic :: Security
Requires-Python: >=3.11
License-File: LICENSE.md
Requires-Dist: python-dotenv>=1.1.0
Requires-Dist: pyyaml>=6.0.1
Requires-Dist: asyncio>=3.4.3
Requires-Dist: aioboto3>=15.1.0
Requires-Dist: pytest-cov>=6.0.0
Provides-Extra: s3
Requires-Dist: boto3>=1.28.0; extra == "s3"
Requires-Dist: aioboto3>=12.0.0; extra == "s3"
Provides-Extra: e2b
Requires-Dist: e2b-code-interpreter>=1.2.0; extra == "e2b"
Provides-Extra: test
Requires-Dist: pytest>=8.3.5; extra == "test"
Requires-Dist: pytest-asyncio>=0.21.0; extra == "test"
Requires-Dist: pytest-cov>=4.1.0; extra == "test"
Provides-Extra: dev
Requires-Dist: pytest>=8.3.5; extra == "dev"
Requires-Dist: pytest-asyncio>=0.21.0; extra == "dev"
Requires-Dist: pytest-cov>=4.1.0; extra == "dev"
Requires-Dist: ruff>=0.6.0; extra == "dev"
Requires-Dist: black>=24.1.0; extra == "dev"
Requires-Dist: isort>=5.12.0; extra == "dev"
Requires-Dist: mypy>=1.8.0; extra == "dev"
Requires-Dist: types-requests>=2.31.0; extra == "dev"
Requires-Dist: bandit>=1.7.5; extra == "dev"
Requires-Dist: bandit[toml]>=1.7.5; extra == "dev"
Requires-Dist: build>=1.0.0; extra == "dev"
Requires-Dist: twine>=4.0.0; extra == "dev"
Requires-Dist: mkdocs>=1.5.0; extra == "dev"
Requires-Dist: mkdocs-material>=9.0.0; extra == "dev"
Dynamic: license-file
